{
  "annotations": {
    "changelogDate": "20251127154319"
  },
  "applications": "*",
  "dto": "mapstruct",
  "fields": [
    {
      "fieldName": "canRead",
      "fieldType": "Boolean",
      "fieldValidateRules": ["required"]
    },
    {
      "fieldName": "canCreate",
      "fieldType": "Boolean",
      "fieldValidateRules": ["required"]
    },
    {
      "fieldName": "canUpdate",
      "fieldType": "Boolean",
      "fieldValidateRules": ["required"]
    },
    {
      "fieldName": "canDelete",
      "fieldType": "Boolean",
      "fieldValidateRules": ["required"]
    }
  ],
  "jpaMetamodelFiltering": true,
  "name": "RolePermission",
  "pagination": "pagination",
  "relationships": [
    {
      "otherEntityName": "role",
      "relationshipName": "role",
      "relationshipSide": "left",
      "relationshipType": "many-to-one",
      "relationshipValidateRules": "required"
    },
    {
      "otherEntityName": "permissionModule",
      "relationshipName": "module",
      "relationshipSide": "left",
      "relationshipType": "many-to-one",
      "relationshipValidateRules": "required"
    }
  ],
  "searchEngine": "no",
  "service": "serviceClass"
}
