<?xml version="1.0" encoding="utf-8"?>
<databaseChangeLog
    xmlns="http://www.liquibase.org/xml/ns/dbchangelog"
    xmlns:xsi="http://www.w3.org/2001/XMLSchema-instance"
    xsi:schemaLocation="http://www.liquibase.org/xml/ns/dbchangelog http://www.liquibase.org/xml/ns/dbchangelog/dbchangelog-latest.xsd">

    <!-- Add audit columns to all entity tables -->

    <changeSet id="20251127160000-1" author="jhipster">
        <addColumn tableName="system_user">
            <column name="created_by" type="varchar(50)" defaultValue="system">
                <constraints nullable="false"/>
            </column>
            <column name="created_date" type="${datetimeType}" defaultValueComputed="${now}"/>
            <column name="last_modified_by" type="varchar(50)"/>
            <column name="last_modified_date" type="${datetimeType}"/>
        </addColumn>
    </changeSet>

    <changeSet id="20251127160000-2" author="jhipster">
        <addColumn tableName="plan">
            <column name="created_by" type="varchar(50)" defaultValue="system">
                <constraints nullable="false"/>
            </column>
            <column name="created_date" type="${datetimeType}" defaultValueComputed="${now}"/>
            <column name="last_modified_by" type="varchar(50)"/>
            <column name="last_modified_date" type="${datetimeType}"/>
        </addColumn>
    </changeSet>

    <changeSet id="20251127160000-3" author="jhipster">
        <addColumn tableName="tenant">
            <column name="created_by" type="varchar(50)" defaultValue="system">
                <constraints nullable="false"/>
            </column>
            <column name="created_date" type="${datetimeType}" defaultValueComputed="${now}"/>
            <column name="last_modified_by" type="varchar(50)"/>
            <column name="last_modified_date" type="${datetimeType}"/>
        </addColumn>
    </changeSet>

    <changeSet id="20251127160000-4" author="jhipster">
        <addColumn tableName="tenant_subscription">
            <column name="created_by" type="varchar(50)" defaultValue="system">
                <constraints nullable="false"/>
            </column>
            <column name="created_date" type="${datetimeType}" defaultValueComputed="${now}"/>
            <column name="last_modified_by" type="varchar(50)"/>
            <column name="last_modified_date" type="${datetimeType}"/>
        </addColumn>
    </changeSet>

    <changeSet id="20251127160000-5" author="jhipster">
        <addColumn tableName="tenant_encryption_key">
            <column name="created_by" type="varchar(50)" defaultValue="system">
                <constraints nullable="false"/>
            </column>
            <column name="created_date" type="${datetimeType}" defaultValueComputed="${now}"/>
            <column name="last_modified_by" type="varchar(50)"/>
            <column name="last_modified_date" type="${datetimeType}"/>
        </addColumn>
    </changeSet>

    <changeSet id="20251127160000-6" author="jhipster">
        <addColumn tableName="country">
            <column name="created_by" type="varchar(50)" defaultValue="system">
                <constraints nullable="false"/>
            </column>
            <column name="created_date" type="${datetimeType}" defaultValueComputed="${now}"/>
            <column name="last_modified_by" type="varchar(50)"/>
            <column name="last_modified_date" type="${datetimeType}"/>
        </addColumn>
    </changeSet>

    <changeSet id="20251127160000-7" author="jhipster">
        <addColumn tableName="state">
            <column name="created_by" type="varchar(50)" defaultValue="system">
                <constraints nullable="false"/>
            </column>
            <column name="created_date" type="${datetimeType}" defaultValueComputed="${now}"/>
            <column name="last_modified_by" type="varchar(50)"/>
            <column name="last_modified_date" type="${datetimeType}"/>
        </addColumn>
    </changeSet>

    <changeSet id="20251127160000-8" author="jhipster">
        <addColumn tableName="city">
            <column name="created_by" type="varchar(50)" defaultValue="system">
                <constraints nullable="false"/>
            </column>
            <column name="created_date" type="${datetimeType}" defaultValueComputed="${now}"/>
            <column name="last_modified_by" type="varchar(50)"/>
            <column name="last_modified_date" type="${datetimeType}"/>
        </addColumn>
    </changeSet>

    <changeSet id="20251127160000-9" author="jhipster">
        <addColumn tableName="address">
            <column name="created_by" type="varchar(50)" defaultValue="system">
                <constraints nullable="false"/>
            </column>
            <column name="created_date" type="${datetimeType}" defaultValueComputed="${now}"/>
            <column name="last_modified_by" type="varchar(50)"/>
            <column name="last_modified_date" type="${datetimeType}"/>
        </addColumn>
    </changeSet>

    <changeSet id="20251127160000-10" author="jhipster">
        <addColumn tableName="tenant_profile">
            <column name="created_by" type="varchar(50)" defaultValue="system">
                <constraints nullable="false"/>
            </column>
            <column name="created_date" type="${datetimeType}" defaultValueComputed="${now}"/>
            <column name="last_modified_by" type="varchar(50)"/>
            <column name="last_modified_date" type="${datetimeType}"/>
        </addColumn>
    </changeSet>

    <changeSet id="20251127160000-11" author="jhipster">
        <addColumn tableName="tenant_branding">
            <column name="created_by" type="varchar(50)" defaultValue="system">
                <constraints nullable="false"/>
            </column>
            <column name="created_date" type="${datetimeType}" defaultValueComputed="${now}"/>
            <column name="last_modified_by" type="varchar(50)"/>
            <column name="last_modified_date" type="${datetimeType}"/>
        </addColumn>
    </changeSet>

    <changeSet id="20251127160000-12" author="jhipster">
        <addColumn tableName="mt_user">
            <column name="created_by" type="varchar(50)" defaultValue="system">
                <constraints nullable="false"/>
            </column>
            <column name="created_date" type="${datetimeType}" defaultValueComputed="${now}"/>
            <column name="last_modified_by" type="varchar(50)"/>
            <column name="last_modified_date" type="${datetimeType}"/>
        </addColumn>
    </changeSet>

    <changeSet id="20251127160000-13" author="jhipster">
        <addColumn tableName="role">
            <column name="created_by" type="varchar(50)" defaultValue="system">
                <constraints nullable="false"/>
            </column>
            <column name="created_date" type="${datetimeType}" defaultValueComputed="${now}"/>
            <column name="last_modified_by" type="varchar(50)"/>
            <column name="last_modified_date" type="${datetimeType}"/>
        </addColumn>
    </changeSet>

    <changeSet id="20251127160000-14" author="jhipster">
        <addColumn tableName="user_role">
            <column name="created_by" type="varchar(50)" defaultValue="system">
                <constraints nullable="false"/>
            </column>
            <column name="created_date" type="${datetimeType}" defaultValueComputed="${now}"/>
            <column name="last_modified_by" type="varchar(50)"/>
            <column name="last_modified_date" type="${datetimeType}"/>
        </addColumn>
    </changeSet>

    <changeSet id="20251127160000-15" author="jhipster">
        <addColumn tableName="permission_module">
            <column name="created_by" type="varchar(50)" defaultValue="system">
                <constraints nullable="false"/>
            </column>
            <column name="created_date" type="${datetimeType}" defaultValueComputed="${now}"/>
            <column name="last_modified_by" type="varchar(50)"/>
            <column name="last_modified_date" type="${datetimeType}"/>
        </addColumn>
    </changeSet>

    <changeSet id="20251127160000-16" author="jhipster">
        <addColumn tableName="role_permission">
            <column name="created_by" type="varchar(50)" defaultValue="system">
                <constraints nullable="false"/>
            </column>
            <column name="created_date" type="${datetimeType}" defaultValueComputed="${now}"/>
            <column name="last_modified_by" type="varchar(50)"/>
            <column name="last_modified_date" type="${datetimeType}"/>
        </addColumn>
    </changeSet>

    <changeSet id="20251127160000-17" author="jhipster">
        <addColumn tableName="user_hierarchy">
            <column name="created_by" type="varchar(50)" defaultValue="system">
                <constraints nullable="false"/>
            </column>
            <column name="created_date" type="${datetimeType}" defaultValueComputed="${now}"/>
            <column name="last_modified_by" type="varchar(50)"/>
            <column name="last_modified_date" type="${datetimeType}"/>
        </addColumn>
    </changeSet>

    <changeSet id="20251127160000-18" author="jhipster">
        <addColumn tableName="department">
            <column name="created_by" type="varchar(50)" defaultValue="system">
                <constraints nullable="false"/>
            </column>
            <column name="created_date" type="${datetimeType}" defaultValueComputed="${now}"/>
            <column name="last_modified_by" type="varchar(50)"/>
            <column name="last_modified_date" type="${datetimeType}"/>
        </addColumn>
    </changeSet>

    <changeSet id="20251127160000-19" author="jhipster">
        <addColumn tableName="user_department">
            <column name="created_by" type="varchar(50)" defaultValue="system">
                <constraints nullable="false"/>
            </column>
            <column name="created_date" type="${datetimeType}" defaultValueComputed="${now}"/>
            <column name="last_modified_by" type="varchar(50)"/>
            <column name="last_modified_date" type="${datetimeType}"/>
        </addColumn>
    </changeSet>

    <changeSet id="20251127160000-20" author="jhipster">
        <addColumn tableName="customer">
            <column name="created_by" type="varchar(50)" defaultValue="system">
                <constraints nullable="false"/>
            </column>
            <column name="created_date" type="${datetimeType}" defaultValueComputed="${now}"/>
            <column name="last_modified_by" type="varchar(50)"/>
            <column name="last_modified_date" type="${datetimeType}"/>
        </addColumn>
    </changeSet>

    <changeSet id="20251127160000-21" author="jhipster">
        <addColumn tableName="contact">
            <column name="created_by" type="varchar(50)" defaultValue="system">
                <constraints nullable="false"/>
            </column>
            <column name="created_date" type="${datetimeType}" defaultValueComputed="${now}"/>
            <column name="last_modified_by" type="varchar(50)"/>
            <column name="last_modified_date" type="${datetimeType}"/>
        </addColumn>
    </changeSet>

    <changeSet id="20251127160000-22" author="jhipster">
        <addColumn tableName="lead_source">
            <column name="created_by" type="varchar(50)" defaultValue="system">
                <constraints nullable="false"/>
            </column>
            <column name="created_date" type="${datetimeType}" defaultValueComputed="${now}"/>
            <column name="last_modified_by" type="varchar(50)"/>
            <column name="last_modified_date" type="${datetimeType}"/>
        </addColumn>
    </changeSet>

    <changeSet id="20251127160000-23" author="jhipster">
        <addColumn tableName="pipeline">
            <column name="created_by" type="varchar(50)" defaultValue="system">
                <constraints nullable="false"/>
            </column>
            <column name="created_date" type="${datetimeType}" defaultValueComputed="${now}"/>
            <column name="last_modified_by" type="varchar(50)"/>
            <column name="last_modified_date" type="${datetimeType}"/>
        </addColumn>
    </changeSet>

    <changeSet id="20251127160000-24" author="jhipster">
        <addColumn tableName="sub_pipeline">
            <column name="created_by" type="varchar(50)" defaultValue="system">
                <constraints nullable="false"/>
            </column>
            <column name="created_date" type="${datetimeType}" defaultValueComputed="${now}"/>
            <column name="last_modified_by" type="varchar(50)"/>
            <column name="last_modified_date" type="${datetimeType}"/>
        </addColumn>
    </changeSet>

    <changeSet id="20251127160000-25" author="jhipster">
        <addColumn tableName="product">
            <column name="created_by" type="varchar(50)" defaultValue="system">
                <constraints nullable="false"/>
            </column>
            <column name="created_date" type="${datetimeType}" defaultValueComputed="${now}"/>
            <column name="last_modified_by" type="varchar(50)"/>
            <column name="last_modified_date" type="${datetimeType}"/>
        </addColumn>
    </changeSet>

    <changeSet id="20251127160000-26" author="jhipster">
        <addColumn tableName="lead">
            <column name="created_by" type="varchar(50)" defaultValue="system">
                <constraints nullable="false"/>
            </column>
            <column name="created_date" type="${datetimeType}" defaultValueComputed="${now}"/>
            <column name="last_modified_by" type="varchar(50)"/>
            <column name="last_modified_date" type="${datetimeType}"/>
        </addColumn>
    </changeSet>

    <changeSet id="20251127160000-27" author="jhipster">
        <addColumn tableName="deal">
            <column name="created_by" type="varchar(50)" defaultValue="system">
                <constraints nullable="false"/>
            </column>
            <column name="created_date" type="${datetimeType}" defaultValueComputed="${now}"/>
            <column name="last_modified_by" type="varchar(50)"/>
            <column name="last_modified_date" type="${datetimeType}"/>
        </addColumn>
    </changeSet>

    <changeSet id="20251127160000-28" author="jhipster">
        <addColumn tableName="quotation">
            <column name="created_by" type="varchar(50)" defaultValue="system">
                <constraints nullable="false"/>
            </column>
            <column name="created_date" type="${datetimeType}" defaultValueComputed="${now}"/>
            <column name="last_modified_by" type="varchar(50)"/>
            <column name="last_modified_date" type="${datetimeType}"/>
        </addColumn>
    </changeSet>

    <changeSet id="20251127160000-29" author="jhipster">
        <addColumn tableName="quotation_item">
            <column name="created_by" type="varchar(50)" defaultValue="system">
                <constraints nullable="false"/>
            </column>
            <column name="created_date" type="${datetimeType}" defaultValueComputed="${now}"/>
            <column name="last_modified_by" type="varchar(50)"/>
            <column name="last_modified_date" type="${datetimeType}"/>
        </addColumn>
    </changeSet>

    <changeSet id="20251127160000-30" author="jhipster">
        <addColumn tableName="complaint_category">
            <column name="created_by" type="varchar(50)" defaultValue="system">
                <constraints nullable="false"/>
            </column>
            <column name="created_date" type="${datetimeType}" defaultValueComputed="${now}"/>
            <column name="last_modified_by" type="varchar(50)"/>
            <column name="last_modified_date" type="${datetimeType}"/>
        </addColumn>
    </changeSet>

    <changeSet id="20251127160000-31" author="jhipster">
        <addColumn tableName="complaint">
            <column name="created_by" type="varchar(50)" defaultValue="system">
                <constraints nullable="false"/>
            </column>
            <column name="created_date" type="${datetimeType}" defaultValueComputed="${now}"/>
            <column name="last_modified_by" type="varchar(50)"/>
            <column name="last_modified_date" type="${datetimeType}"/>
        </addColumn>
    </changeSet>

    <changeSet id="20251127160000-32" author="jhipster">
        <addColumn tableName="ticket">
            <column name="created_by" type="varchar(50)" defaultValue="system">
                <constraints nullable="false"/>
            </column>
            <column name="created_date" type="${datetimeType}" defaultValueComputed="${now}"/>
            <column name="last_modified_by" type="varchar(50)"/>
            <column name="last_modified_date" type="${datetimeType}"/>
        </addColumn>
    </changeSet>

    <changeSet id="20251127160000-33" author="jhipster">
        <addColumn tableName="task_type">
            <column name="created_by" type="varchar(50)" defaultValue="system">
                <constraints nullable="false"/>
            </column>
            <column name="created_date" type="${datetimeType}" defaultValueComputed="${now}"/>
            <column name="last_modified_by" type="varchar(50)"/>
            <column name="last_modified_date" type="${datetimeType}"/>
        </addColumn>
    </changeSet>

    <changeSet id="20251127160000-34" author="jhipster">
        <addColumn tableName="task">
            <column name="created_by" type="varchar(50)" defaultValue="system">
                <constraints nullable="false"/>
            </column>
            <column name="created_date" type="${datetimeType}" defaultValueComputed="${now}"/>
            <column name="last_modified_by" type="varchar(50)"/>
            <column name="last_modified_date" type="${datetimeType}"/>
        </addColumn>
    </changeSet>

    <changeSet id="20251127160000-35" author="jhipster">
        <addColumn tableName="task_comment">
            <column name="created_by" type="varchar(50)" defaultValue="system">
                <constraints nullable="false"/>
            </column>
            <column name="created_date" type="${datetimeType}" defaultValueComputed="${now}"/>
            <column name="last_modified_by" type="varchar(50)"/>
            <column name="last_modified_date" type="${datetimeType}"/>
        </addColumn>
    </changeSet>

    <changeSet id="20251127160000-36" author="jhipster">
        <addColumn tableName="event">
            <column name="created_by" type="varchar(50)" defaultValue="system">
                <constraints nullable="false"/>
            </column>
            <column name="created_date" type="${datetimeType}" defaultValueComputed="${now}"/>
            <column name="last_modified_by" type="varchar(50)"/>
            <column name="last_modified_date" type="${datetimeType}"/>
        </addColumn>
    </changeSet>

    <changeSet id="20251127160000-37" author="jhipster">
        <addColumn tableName="event_task_assignment">
            <column name="created_by" type="varchar(50)" defaultValue="system">
                <constraints nullable="false"/>
            </column>
            <column name="created_date" type="${datetimeType}" defaultValueComputed="${now}"/>
            <column name="last_modified_by" type="varchar(50)"/>
            <column name="last_modified_date" type="${datetimeType}"/>
        </addColumn>
    </changeSet>

    <changeSet id="20251127160000-38" author="jhipster">
        <addColumn tableName="notification">
            <column name="created_by" type="varchar(50)" defaultValue="system">
                <constraints nullable="false"/>
            </column>
            <column name="created_date" type="${datetimeType}" defaultValueComputed="${now}"/>
            <column name="last_modified_by" type="varchar(50)"/>
            <column name="last_modified_date" type="${datetimeType}"/>
        </addColumn>
    </changeSet>

    <changeSet id="20251127160000-39" author="jhipster">
        <addColumn tableName="event_notification">
            <column name="created_by" type="varchar(50)" defaultValue="system">
                <constraints nullable="false"/>
            </column>
            <column name="created_date" type="${datetimeType}" defaultValueComputed="${now}"/>
            <column name="last_modified_by" type="varchar(50)"/>
            <column name="last_modified_date" type="${datetimeType}"/>
        </addColumn>
    </changeSet>

    <changeSet id="20251127160000-40" author="jhipster">
        <addColumn tableName="report_template">
            <column name="created_by" type="varchar(50)" defaultValue="system">
                <constraints nullable="false"/>
            </column>
            <column name="created_date" type="${datetimeType}" defaultValueComputed="${now}"/>
            <column name="last_modified_by" type="varchar(50)"/>
            <column name="last_modified_date" type="${datetimeType}"/>
        </addColumn>
    </changeSet>

    <changeSet id="20251127160000-41" author="jhipster">
        <addColumn tableName="report_run">
            <column name="created_by" type="varchar(50)" defaultValue="system">
                <constraints nullable="false"/>
            </column>
            <column name="created_date" type="${datetimeType}" defaultValueComputed="${now}"/>
            <column name="last_modified_by" type="varchar(50)"/>
            <column name="last_modified_date" type="${datetimeType}"/>
        </addColumn>
    </changeSet>

    <changeSet id="20251127160000-42" author="jhipster">
        <addColumn tableName="audit_log">
            <column name="created_by" type="varchar(50)" defaultValue="system">
                <constraints nullable="false"/>
            </column>
            <column name="created_date" type="${datetimeType}" defaultValueComputed="${now}"/>
            <column name="last_modified_by" type="varchar(50)"/>
            <column name="last_modified_date" type="${datetimeType}"/>
        </addColumn>
    </changeSet>

</databaseChangeLog>
